agewizard/__init__.py
agewizard/core.py
agewizard-0.2.1.dist-info/licenses/LICENSE
agewizard-0.2.1.dist-info/METADATA
agewizard-0.2.1.dist-info/WHEEL
agewizard-0.2.1.dist-info/top_level.txt
agewizard-0.2.1.dist-info/RECORD
