Metadata-Version: 2.4
Name: agewizard
Version: 0.2.1
Summary: A powerful age calculator library
Home-page: https://github.com/KamranProjects/agewizard
Author: Kamran Hussain
Author-email: contact.kamrankami@gmail.com
Classifier: Programming Language :: Python :: 3
Classifier: License :: OSI Approved :: MIT License
Classifier: Operating System :: OS Independent
Requires-Python: >=3.6
License-File: LICENSE
Dynamic: author
Dynamic: author-email
Dynamic: classifier
Dynamic: description
Dynamic: description-content-type
Dynamic: home-page
Dynamic: license-file
Dynamic: requires-python
Dynamic: summary
